{"title":"Combined feed","url":"https://ITCORD.github.io/techm/all.xml","elements":[{"title":"야놀자, 놀데이 캠페인 '워터파크'편 눈길…물놀이 최대 94% 할인 (테크M ─ 전체기사)","contents":"이수호 기자","link":"https://www.techm.kr/news/articleView.html?idxno=125968","retrieved":1718272800000,"image":"https://www.techm.kr/news/thumbnail/202406/125968_162641_028_v150.jpg"},{"title":"스마일게이트 희망스튜디오 '호프 크리에이터' 5기 33명 모집 (테크M ─ 전체기사)","contents":"임경호 기자","link":"https://www.techm.kr/news/articleView.html?idxno=125961","retrieved":1718272740000,"image":"https://www.techm.kr/news/thumbnail/202406/125961_162636_4858_v150.jpg"},{"title":"삼성전자, 미국서 '삼성 파운드리 포럼 2024' 진행…AI 커스텀 파운드리 전략 공개 (테크M ─ 전체기사)","contents":"배수현 기자","link":"https://www.techm.kr/news/articleView.html?idxno=125960","retrieved":1718272740000,"image":"https://www.techm.kr/news/thumbnail/202406/125960_162637_5355_v150.jpg"},{"title":"솔드아웃, 정품 검수 B2B 비즈니스 '확대' (테크M ─ 전체기사)","contents":"이수호 기자","link":"https://www.techm.kr/news/articleView.html?idxno=125966","retrieved":1718272620000,"image":"https://www.techm.kr/news/thumbnail/202406/125966_162640_5753_v150.jpg"},{"title":"이마트, 주말 특가 행사 '과일데이' 활짝...수박 최대 30% 할인 (테크M ─ 전체기사)","contents":"이수호 기자","link":"https://www.techm.kr/news/articleView.html?idxno=125965","retrieved":1718272560000,"image":"https://www.techm.kr/news/thumbnail/202406/125965_162639_563_v150.jpg"},{"title":"지그재그, 카카오 '톡학생증' 제휴 프로모션...대학생 고객 겨냥 (테크M ─ 전체기사)","contents":"이수호 기자","link":"https://www.techm.kr/news/articleView.html?idxno=125963","retrieved":1718272440000,"image":"https://www.techm.kr/news/thumbnail/202406/125963_162638_5439_v150.jpg"},{"title":"이번엔 축구다...티빙 '유로 2024' 전 경기 생중계 (테크M ─ 전체기사)","contents":"임경호 기자","link":"https://www.techm.kr/news/articleView.html?idxno=125957","retrieved":1718271960000,"image":"https://www.techm.kr/news/thumbnail/202406/125957_162635_438_v150.jpg"},{"title":"'즉석밥'에 K푸드 '소울' 담았다...하림, '더미식 요리밥' 3종 출시 (테크M ─ 전체기사)","contents":"이소라 기자","link":"https://www.techm.kr/news/articleView.html?idxno=125958","retrieved":1718271720000,"image":"https://www.techm.kr/news/thumbnail/202406/125958_162634_4037_v150.jpg"},{"title":"[크립토 브리핑] 美 기준금리 동결...비트코인은 제자리걸음 (테크M ─ 전체기사)","contents":"이성우 기자","link":"https://www.techm.kr/news/articleView.html?idxno=125955","retrieved":1718271420000,"image":"https://www.techm.kr/news/thumbnail/202406/125955_162631_242_v150.jpg"},{"title":"CJ제일제당, 햇반 잡곡 집중 프로모션...\"햇반의 집밥화에 박차\" (테크M ─ 전체기사)","contents":"이소라 기자","link":"https://www.techm.kr/news/articleView.html?idxno=125956","retrieved":1718271060000,"image":"https://www.techm.kr/news/thumbnail/202406/125956_162633_2932_v150.jpg"},{"title":"국산 쌀가루의 매콤한 변신...농심, 별미복음면 매콤찜닭맛 출시 (테크M ─ 전체기사)","contents":"이소라 기자","link":"https://www.techm.kr/news/articleView.html?idxno=125954","retrieved":1718270700000,"image":"https://www.techm.kr/news/thumbnail/202406/125954_162632_2430_v150.jpg"},{"title":"5개월 만에 개발한 게임, 앱스토어 매출 3위 등극...캐주얼 게임 개발 탄력 붙을까 (테크M ─ 전체기사)","contents":"임경호 기자","link":"https://www.techm.kr/news/articleView.html?idxno=125950","retrieved":1718265600000,"image":"https://www.techm.kr/news/thumbnail/202406/125950_162627_1255_v150.jpg"},{"title":"[게임코인TV] 금융위가 NFT 가이드라인을 발표했다...NFT도 가상자산일까?(2편) (테크M ─ 전체기사)","contents":"이소라 기자","link":"https://www.techm.kr/news/articleView.html?idxno=125953","retrieved":1718201829914,"image":"https://www.techm.kr/news/thumbnail/202406/125953_162630_959_v150.jpg"},{"title":"\"끝없는 욕심\" 홍원식 남양유업 전 회장의 셀프 퇴직금 443억?...유통가 비난 '쇄도' (테크M ─ 전체기사)","contents":"이수호 기자","link":"https://www.techm.kr/news/articleView.html?idxno=125951","retrieved":1718183910144,"image":"https://www.techm.kr/news/thumbnail/202406/125951_162629_5139_v150.jpg"},{"title":"생성형 AI 활용 저작권 문제, 다른 나라는 어떻게?...\"저작권자·이용자 양측 이해 필요\" (테크M ─ 전체기사)","contents":"임경호 기자","link":"https://www.techm.kr/news/articleView.html?idxno=125949","retrieved":1718180523863,"image":"https://www.techm.kr/news/thumbnail/202406/125949_162625_4311_v150.jpg"},{"title":"SKT, 사피온코리아·리벨리온 합병 추진…연내 국가대표 AI반도체 기업 띄운다 (테크M ─ 전체기사)","contents":"조성준 기자","link":"https://www.techm.kr/news/articleView.html?idxno=125934","retrieved":1718176648018,"image":"https://www.techm.kr/news/thumbnail/202406/125934_162586_3050_v150.jpg"},{"title":"[테크M 이슈] AI반도체 '적과의 동침' 결정한 SKT·KT...사피온·리벨리온 합병으로 '베지트' 탄생 (테크M ─ 전체기사)","contents":"조성준 기자","link":"https://www.techm.kr/news/articleView.html?idxno=125946","retrieved":1718176648030,"image":"https://www.techm.kr/news/thumbnail/202406/125946_162617_1540_v150.jpg"},{"title":"\"북미 B2B 시장 잡아라\"...삼성·LG, 전사적으로 북미 공략 나선 이유는 (테크M ─ 전체기사)","contents":"배수현 기자","link":"https://www.techm.kr/news/articleView.html?idxno=125942","retrieved":1718176648032,"image":"https://www.techm.kr/news/thumbnail/202406/125942_162618_165_v150.jpg"},{"title":"[인디이콘의 경제M] 올 하반기 주식시장 전망 \"기업실적과 시장의 펀더멘털을 보자\" (테크M ─ 전체기사)","contents":"김현기 대표","link":"https://www.techm.kr/news/articleView.html?idxno=125947","retrieved":1718183910161,"image":"https://www.techm.kr/news/thumbnail/202406/125947_162614_4453_v150.jpg"},{"title":"[테크M 프리미엄] CDMA와 '혁신 DNA' 외친 SK텔레콤...최태원의 '특혜' 아니라는 항변 (테크M ─ 전체기사)","contents":"허준 편집장","link":"https://www.techm.kr/news/articleView.html?idxno=125948","retrieved":1718183910162,"image":"https://www.techm.kr/news/thumbnail/202406/125948_162624_204_v150.jpg"},{"title":"스마일게이트 희망스튜디오 '호프 크리에이터' 5기 33명 모집 (테크M ─ 콘텐츠)","contents":"임경호 기자","link":"https://www.techm.kr/news/articleView.html?idxno=125961","retrieved":1718272740000,"image":"https://www.techm.kr/news/thumbnail/202406/125961_162636_4858_v150.jpg"},{"title":"이번엔 축구다...티빙 '유로 2024' 전 경기 생중계 (테크M ─ 콘텐츠)","contents":"임경호 기자","link":"https://www.techm.kr/news/articleView.html?idxno=125957","retrieved":1718271960000,"image":"https://www.techm.kr/news/thumbnail/202406/125957_162635_438_v150.jpg"},{"title":"5개월 만에 개발한 게임, 앱스토어 매출 3위 등극...캐주얼 게임 개발 탄력 붙을까 (테크M ─ 콘텐츠)","contents":"임경호 기자","link":"https://www.techm.kr/news/articleView.html?idxno=125950","retrieved":1718265600000,"image":"https://www.techm.kr/news/thumbnail/202406/125950_162627_1255_v150.jpg"},{"title":"생성형 AI 활용 저작권 문제, 다른 나라는 어떻게?...\"저작권자·이용자 양측 이해 필요\" (테크M ─ 콘텐츠)","contents":"임경호 기자","link":"https://www.techm.kr/news/articleView.html?idxno=125949","retrieved":1718180523863,"image":"https://www.techm.kr/news/thumbnail/202406/125949_162625_4311_v150.jpg"},{"title":"이건복 MS 상무 \"생성형 AI는 창작 위한 보조 수단...기술 발전 적응해나가야\" (테크M ─ 콘텐츠)","contents":"임경호 기자","link":"https://www.techm.kr/news/articleView.html?idxno=125938","retrieved":1718176624760,"image":"https://www.techm.kr/news/thumbnail/202406/125938_162590_2355_v150.jpg"},{"title":"카카오게임즈, '패스 오브 엑자일 2' 위치 시연 영상 공개 (테크M ─ 콘텐츠)","contents":"임경호 기자","link":"https://www.techm.kr/news/articleView.html?idxno=125944","retrieved":1718176624762,"image":"https://www.techm.kr/news/thumbnail/202406/125944_162600_1521_v150.jpg"},{"title":"NHN클라우드, 일본 대표 IT 행사 참가...현지 시장 공략 가속화 (테크M ─ 콘텐츠)","contents":"임경호 기자","link":"https://www.techm.kr/news/articleView.html?idxno=125943","retrieved":1718176624763,"image":"https://www.techm.kr/news/thumbnail/202406/125943_162595_935_v150.jpg"},{"title":"데브시스터즈, 쿠키런 대축제 'Happy Brave Festa' 개최...'용감한 쿠키' 15번째 생일 기념 (테크M ─ 콘텐츠)","contents":"임경호 기자","link":"https://www.techm.kr/news/articleView.html?idxno=125937","retrieved":1718173471968,"image":"https://www.techm.kr/news/thumbnail/202406/125937_162589_1232_v150.jpg"},{"title":"위메이드커넥트, '미르의 전설2: 기연' 원스토어 공개 테스트 시작 (테크M ─ 콘텐츠)","contents":"임경호 기자","link":"https://www.techm.kr/news/articleView.html?idxno=125936","retrieved":1718169390130,"image":"https://www.techm.kr/news/thumbnail/202406/125936_162588_487_v150.jpg"},{"title":"\"광고제거 BM 끝났다\" 구글플레이 패스 출격...韓 모바일 게임 판도 바꿀까 (테크M ─ 콘텐츠)","contents":"이수호 기자","link":"https://www.techm.kr/news/articleView.html?idxno=125932","retrieved":1718151780000,"image":"https://www.techm.kr/news/thumbnail/202406/125932_162620_1648_v150.jpg"},{"title":"[LCK 브리핑] 젠지, 5연패 향한 항해 시작...라이벌 T1 꺾고 가능성 높일까 (테크M ─ 콘텐츠)","contents":"이소라 기자","link":"https://www.techm.kr/news/articleView.html?idxno=125914","retrieved":1718187660000,"image":"https://www.techm.kr/news/thumbnail/202406/125914_162557_1139_v150.jpg"},{"title":"모바일 전략게임 '로드 모바일'에서 쿠사나기 쿄 만난다...'KOF XV'와 컬래버 (테크M ─ 콘텐츠)","contents":"임경호 기자","link":"https://www.techm.kr/news/articleView.html?idxno=125915","retrieved":1718187300000,"image":"https://www.techm.kr/news/thumbnail/202406/125915_162555_946_v150.jpg"},{"title":"'남남 로맨스' 돌아왔다...웨이브 오리지널 '남의 연애' 시즌3 21일 공개 (테크M ─ 콘텐츠)","contents":"임경호 기자","link":"https://www.techm.kr/news/articleView.html?idxno=125912","retrieved":1718186820000,"image":"https://www.techm.kr/news/thumbnail/202406/125912_162554_22_v150.jpg"},{"title":"여자 배구도 쿠팡플레이와 함께...'2024 FIVB 여자 발리볼네이션스리그' 한일전 생중계 (테크M ─ 콘텐츠)","contents":"임경호 기자","link":"https://www.techm.kr/news/articleView.html?idxno=125907","retrieved":1718186520000,"image":"https://www.techm.kr/news/thumbnail/202406/125907_162549_5429_v150.jpg"},{"title":"삼성전자, 미국서 '삼성 파운드리 포럼 2024' 진행…AI 커스텀 파운드리 전략 공개 (테크M ─ 인프라)","contents":"배수현 기자","link":"https://www.techm.kr/news/articleView.html?idxno=125960","retrieved":1718272740000,"image":"https://www.techm.kr/news/thumbnail/202406/125960_162637_5355_v150.jpg"},{"title":"SKT, 사피온코리아·리벨리온 합병 추진…연내 국가대표 AI반도체 기업 띄운다 (테크M ─ 인프라)","contents":"조성준 기자","link":"https://www.techm.kr/news/articleView.html?idxno=125934","retrieved":1718176648018,"image":"https://www.techm.kr/news/thumbnail/202406/125934_162586_3050_v150.jpg"},{"title":"[테크M 이슈] AI반도체 '적과의 동침' 결정한 SKT·KT...사피온·리벨리온 합병으로 '베지트' 탄생 (테크M ─ 인프라)","contents":"조성준 기자","link":"https://www.techm.kr/news/articleView.html?idxno=125946","retrieved":1718176648030,"image":"https://www.techm.kr/news/thumbnail/202406/125946_162617_1540_v150.jpg"},{"title":"\"북미 B2B 시장 잡아라\"...삼성·LG, 전사적으로 북미 공략 나선 이유는 (테크M ─ 인프라)","contents":"배수현 기자","link":"https://www.techm.kr/news/articleView.html?idxno=125942","retrieved":1718176648032,"image":"https://www.techm.kr/news/thumbnail/202406/125942_162618_165_v150.jpg"},{"title":"메타보라 싱가폴, 보라 3.0 업데이트...디플레이션 토크노믹스 적용 (테크M ─ 인프라)","contents":"이수호 기자","link":"https://www.techm.kr/news/articleView.html?idxno=125939","retrieved":1718173493344,"image":"https://www.techm.kr/news/thumbnail/202406/125939_162591_3810_v150.jpg"},{"title":"카카오, 데이터센터 추가 임차·인수 가능성 시사...제2 데이터센터 오픈 일정에 달렸다 (테크M ─ 인프라)","contents":"이성우 기자","link":"https://www.techm.kr/news/articleView.html?idxno=125904","retrieved":1718150520000,"image":"https://www.techm.kr/news/thumbnail/202406/125904_162546_422_v150.jpg"},{"title":"KT꿈품교실 난청아동, '흥민이형' 손잡고 상암 잔디 밟았다 (테크M ─ 인프라)","contents":"배수현 기자","link":"https://www.techm.kr/news/articleView.html?idxno=125928","retrieved":1718193300000,"image":"https://www.techm.kr/news/thumbnail/202406/125928_162578_4441_v150.jpg"},{"title":"방통위, 지상파 재허가 심사 착수…146개 방송국 대상 (테크M ─ 인프라)","contents":"조성준 기자","link":"https://www.techm.kr/news/articleView.html?idxno=125931","retrieved":1718193120000,"image":"https://www.techm.kr/news/thumbnail/202406/125931_162580_525_v150.jpg"},{"title":"효성인포메이션시스템-빔, 하이브리드 클라우드 데이터 보호 현대화 '맞손' (테크M ─ 인프라)","contents":"남도영 기자","link":"https://www.techm.kr/news/articleView.html?idxno=125930","retrieved":1718192820000,"image":"https://www.techm.kr/news/thumbnail/202406/125930_162579_4722_v150.jpg"},{"title":"이노그리드, 서울관광재단 클라우드 구축 및 전환 사업 수주 (테크M ─ 인프라)","contents":"남도영 기자","link":"https://www.techm.kr/news/articleView.html?idxno=125929","retrieved":1718192640000,"image":"https://www.techm.kr/news/thumbnail/202406/125929_162577_4431_v150.jpg"},{"title":"방통위, 위치정보보호 위반 사업자에 과징금 8억5600만원 부과 (테크M ─ 인프라)","contents":"조성준 기자","link":"https://www.techm.kr/news/articleView.html?idxno=125927","retrieved":1718192160000,"image":"https://www.techm.kr/news/thumbnail/202406/125927_162576_3612_v150.jpg"},{"title":"[테크M 이슈] 2년새 또 거듭된 횡령...조병규의 우리은행이 흔들린다 (테크M ─ 인프라)","contents":"이수호 기자","link":"https://www.techm.kr/news/articleView.html?idxno=125926","retrieved":1718189160000,"image":"https://www.techm.kr/news/thumbnail/202406/125926_162574_4656_v150.jpg"},{"title":"'아이폰16' vs. '갤Z폴드6·플립6'...하반기 'AI폰 대전' 펼쳐진다 (테크M ─ 인프라)","contents":"남도영 기자","link":"https://www.techm.kr/news/articleView.html?idxno=125924","retrieved":1718188860000,"image":"https://www.techm.kr/news/thumbnail/202406/125924_162623_1942_v150.jpg"},{"title":"개인고객 1500만 규모 'KB국민인증서' 기업고객까지 인증서비스 확대 (테크M ─ 인프라)","contents":"이수호 기자","link":"https://www.techm.kr/news/articleView.html?idxno=125925","retrieved":1718188560000,"image":"https://www.techm.kr/news/thumbnail/202406/125925_162572_362_v150.jpg"},{"title":"\"현재 유통되는 NFT는 대부분 가상자산이다\"...법조계 \"가상자산사업자 등록해야\" (테크M ─ 이노베이션)","contents":"이성우 기자","link":"https://www.techm.kr/news/articleView.html?idxno=125941","retrieved":1718183910162,"image":"https://www.techm.kr/news/thumbnail/202406/125941_162619_1624_v150.jpg"},{"title":"기후테크 전문가 한 자리에…건설연 '기후테크설루션 콘퍼런스' 개최 (테크M ─ 이노베이션)","contents":"남도영 기자","link":"https://www.techm.kr/news/articleView.html?idxno=125940","retrieved":1718173513269,"image":"https://www.techm.kr/news/thumbnail/202406/125940_162592_4224_v150.jpg"},{"title":"지난달 카카오톡 세번 연속 오류, 원인 모두 달랐다...\"데이터센터와 연관 없어\" (테크M ─ 이노베이션)","contents":"이성우 기자","link":"https://www.techm.kr/news/articleView.html?idxno=125901","retrieved":1718150520000,"image":"https://www.techm.kr/news/thumbnail/202406/125901_162544_483_v150.jpg"},{"title":"정신아 카카오 \"이제는 서비스 경쟁...쉬운 AI 서비스 선보일 것\" (테크M ─ 이노베이션)","contents":"이성우 기자","link":"https://www.techm.kr/news/articleView.html?idxno=125900","retrieved":1718150460000,"image":"https://www.techm.kr/news/thumbnail/202406/125900_162543_2345_v150.jpg"},{"title":"'10시간 먹통' 교훈은 '이중화'...'카카오 데이터센터 안산', 국민 일상 지킨다 (테크M ─ 이노베이션)","contents":"이성우 기자","link":"https://www.techm.kr/news/articleView.html?idxno=125897","retrieved":1718150400000,"image":"https://www.techm.kr/news/thumbnail/202406/125897_162622_186_v150.jpg"},{"title":"토스, '정치후원금 보내기' 서비스 개편...후원회와 후원인 편의성 높여 (테크M ─ 이노베이션)","contents":"이성우 기자","link":"https://www.techm.kr/news/articleView.html?idxno=125922","retrieved":1718188380000,"image":"https://www.techm.kr/news/thumbnail/202406/125922_162566_254_v150.jpg"},{"title":"두나무, 자립준비청년 위한 '넥스트 잡' 인턴십 모집 (테크M ─ 이노베이션)","contents":"이성우 기자","link":"https://www.techm.kr/news/articleView.html?idxno=125923","retrieved":1718188380000,"image":"https://www.techm.kr/news/thumbnail/202406/125923_162567_2814_v150.jpg"},{"title":"케이뱅크, 쿠팡 결제 최대 5% 적립해주는 '리워드쇼핑' 출시 (테크M ─ 이노베이션)","contents":"이성우 기자","link":"https://www.techm.kr/news/articleView.html?idxno=125921","retrieved":1718187840000,"image":"https://www.techm.kr/news/thumbnail/202406/125921_162565_2311_v150.jpg"},{"title":"환전·결제를 넘어 여행 정보까지...토스뱅크서 해외 맛집 순위 확인한다 (테크M ─ 이노베이션)","contents":"이성우 기자","link":"https://www.techm.kr/news/articleView.html?idxno=125919","retrieved":1718187840000,"image":"https://www.techm.kr/news/thumbnail/202406/125919_162563_2040_v150.jpg"},{"title":"카톡 기반 CS 챗봇 '챗봇나우', 쇼핑몰 구축 플랫폼 '플렉스지'에 적용 (테크M ─ 이노베이션)","contents":"이성우 기자","link":"https://www.techm.kr/news/articleView.html?idxno=125918","retrieved":1718187840000,"image":"https://www.techm.kr/news/thumbnail/202406/125918_162560_1713_v150.jpg"},{"title":"캐리버스, 카드 전략 RPG '슈퍼콜라 택틱스' 트레일러 영상 공개 (테크M ─ 이노베이션)","contents":"이성우 기자","link":"https://www.techm.kr/news/articleView.html?idxno=125916","retrieved":1718187360000,"image":"https://www.techm.kr/news/thumbnail/202406/125916_162559_1339_v150.jpg"},{"title":"카카오페이, 2024 소상공인 판로 지원 사업에 기금 10억원 전달 (테크M ─ 이노베이션)","contents":"이성우 기자","link":"https://www.techm.kr/news/articleView.html?idxno=125913","retrieved":1718187240000,"image":"https://www.techm.kr/news/thumbnail/202406/125913_162556_1025_v150.jpg"},{"title":"카카오 AI 전담조직 '카나나' 신설...서비스·개발 투트랙 (테크M ─ 이노베이션)","contents":"이성우 기자","link":"https://www.techm.kr/news/articleView.html?idxno=125894","retrieved":1718104539386,"image":"https://www.techm.kr/news/thumbnail/202406/125894_162519_57_v150.jpg"},{"title":"팀스파르타, 전국민 AI 일상화 프로젝트 'AI와 100인의 용사들' 해커톤 개최 (테크M ─ 이노베이션)","contents":"이성우 기자","link":"https://www.techm.kr/news/articleView.html?idxno=125893","retrieved":1718104539388,"image":"https://www.techm.kr/news/thumbnail/202406/125893_162518_2628_v150.jpg"},{"title":"[크립토 브리핑] 美 기준금리 동결...비트코인은 제자리걸음 (테크M ─ 인베스트먼트)","contents":"이성우 기자","link":"https://www.techm.kr/news/articleView.html?idxno=125955","retrieved":1718271420000,"image":"https://www.techm.kr/news/thumbnail/202406/125955_162631_242_v150.jpg"},{"title":"[크립토 브리핑] 1억원 고지 멀어지는 비트코인...9500만원대로 (테크M ─ 인베스트먼트)","contents":"이성우 기자","link":"https://www.techm.kr/news/articleView.html?idxno=125911","retrieved":1718186520000,"image":"https://www.techm.kr/news/thumbnail/202406/125911_162552_16_v150.jpg"},{"title":"[테크M 리포트] 바닥 찍은 카카오게임즈, 보릿고개 넘어 새 모멘텀 띄운다 (테크M ─ 인베스트먼트)","contents":"이수호 기자","link":"https://www.techm.kr/news/articleView.html?idxno=125876","retrieved":1718083099996,"image":"https://www.techm.kr/news/thumbnail/202406/125876_162484_512_v150.jpg"},{"title":"[크립토 브리핑] 금리인하 가능성 없다...비트코인- 이더리움 소폭 하락 (테크M ─ 인베스트먼트)","contents":"이성우 기자","link":"https://www.techm.kr/news/articleView.html?idxno=125838","retrieved":1718097180000,"image":"https://www.techm.kr/news/thumbnail/202406/125838_162444_039_v150.jpg"},{"title":"시프트업 IPO 일정 7월 이후로...투자위험요소 해소 '집중' (테크M ─ 인베스트먼트)","contents":"임경호 기자","link":"https://www.techm.kr/news/articleView.html?idxno=125802","retrieved":1718018400000,"image":"https://www.techm.kr/news/thumbnail/202406/125802_162351_1022_v150.jpg"},{"title":"[크립토 브리핑] 1억원 재돌파는 어렵나...비트코인 닷새째 횡보 (테크M ─ 인베스트먼트)","contents":"이성우 기자","link":"https://www.techm.kr/news/articleView.html?idxno=125780","retrieved":1718013060000,"image":"https://www.techm.kr/news/thumbnail/202406/125780_162324_4442_v150.jpg"},{"title":"[크립토 주간 브리핑] 1억원 향해 가는 비트코인...알트코인은 제자리걸음 (테크M ─ 인베스트먼트)","contents":"이성우 기자","link":"https://www.techm.kr/news/articleView.html?idxno=125746","retrieved":1717841880000,"image":"https://www.techm.kr/news/thumbnail/202406/125746_162258_236_v150.jpg"},{"title":"[테크M 리포트] 펄어비스, 매달 모멘텀 등판...붉은사막 이어 검사로 中 수출길 '활짝' (테크M ─ 인베스트먼트)","contents":"이수호 기자","link":"https://www.techm.kr/news/articleView.html?idxno=125725","retrieved":1717759800000,"image":"https://www.techm.kr/news/thumbnail/202406/125725_162210_2841_v150.jpg"},{"title":"[크립토 브리핑] 상승세 탄 비트코인, 1억원 재돌파 넘본다 (테크M ─ 인베스트먼트)","contents":"이성우 기자","link":"https://www.techm.kr/news/articleView.html?idxno=125705","retrieved":1717754400000,"image":"https://www.techm.kr/news/thumbnail/202406/125705_162183_5720_v150.jpg"},{"title":"뤼튼테크놀로지스, 250억원 규모 프리 시리즈 B 투자 유치 (테크M ─ 인베스트먼트)","contents":"조성준 기자","link":"https://www.techm.kr/news/articleView.html?idxno=125704","retrieved":1717754400000,"image":"https://www.techm.kr/news/thumbnail/202406/125704_162182_562_v150.jpg"},{"title":"모듈러 블록체인 어베일, 시리즈A 투자 유치...누적 투자 금액 7500만달러 (테크M ─ 인베스트먼트)","contents":"이성우 기자","link":"https://www.techm.kr/news/articleView.html?idxno=125657","retrieved":1717568648048,"image":"https://www.techm.kr/news/thumbnail/202406/125657_162102_2920_v150.jpg"},{"title":"[크립토 브리핑] 꾸준히 상승하는 비트코인...1억원 다시 가나 (테크M ─ 인베스트먼트)","contents":"이성우 기자","link":"https://www.techm.kr/news/articleView.html?idxno=125624","retrieved":1717582980000,"image":"https://www.techm.kr/news/thumbnail/202406/125624_162064_115_v150.jpg"},{"title":"[테크M 리포트] 88년생 CEO 앞세운 데브시스터즈...쿠키런 IP로 재도약 신호탄 (테크M ─ 인베스트먼트)","contents":"이수호 기자","link":"https://www.techm.kr/news/articleView.html?idxno=125568","retrieved":1717462620000,"image":"https://www.techm.kr/news/thumbnail/202406/125568_161969_5538_v150.jpg"},{"title":"신범준 토큰증권협의회장 \"STO, 신속한 법 통과 필요...기존 틀에 끼우면 안 된다\" (테크M ─ 인베스트먼트)","contents":"허준 편집장","link":"https://www.techm.kr/news/articleView.html?idxno=125562","retrieved":1717499220000,"image":"https://www.techm.kr/news/thumbnail/202406/125562_161965_726_v150.jpg"},{"title":"\"끝없는 욕심\" 홍원식 남양유업 전 회장의 셀프 퇴직금 443억?...유통가 비난 '쇄도' (테크M ─ 피플)","contents":"이수호 기자","link":"https://www.techm.kr/news/articleView.html?idxno=125951","retrieved":1718183910144,"image":"https://www.techm.kr/news/thumbnail/202406/125951_162629_5139_v150.jpg"},{"title":"정신아 카카오 첫 공식 기자간담회...'데이터센터 안산'에서 시작한 이유 (테크M ─ 피플)","contents":"이성우 기자","link":"https://www.techm.kr/news/articleView.html?idxno=125899","retrieved":1718150460000,"image":"https://www.techm.kr/news/thumbnail/202406/125899_162621_1737_v150.jpg"},{"title":"[e스포츠人] \"반성하고, 노력해야죠\"...고민 깊어진 젠지 펍지팀 (테크M ─ 피플)","contents":"이소라 기자","link":"https://www.techm.kr/news/articleView.html?idxno=125771","retrieved":1717953324369,"image":"https://www.techm.kr/news/thumbnail/202406/125771_162314_4659_v150.jpg"},{"title":"[e스포츠人] 외모만큼 실력도 인정 받은 돌풍의 주역 이원주 (테크M ─ 피플)","contents":"이소라 기자","link":"https://www.techm.kr/news/articleView.html?idxno=125758","retrieved":1717859842769,"image":"https://www.techm.kr/news/thumbnail/202406/125758_162285_5037_v150.jpg"},{"title":"미래 성장동력 찾아 나선 이재용 \"아무도 못하는 사업, 누구보다 먼저 해내자\" (테크M ─ 피플)","contents":"남도영 기자","link":"https://www.techm.kr/news/articleView.html?idxno=125695","retrieved":1717669061837,"image":"https://www.techm.kr/news/thumbnail/202406/125695_162173_2135_v150.jpg"},{"title":"[테크M 이슈] 범삼성가 유통 빅딜...정용진-이재현, 가족의 힘으로 쿠팡에 맞선다 (테크M ─ 피플)","contents":"이수호 기자","link":"https://www.techm.kr/news/articleView.html?idxno=125683","retrieved":1717590728483,"image":"https://www.techm.kr/news/thumbnail/202406/125683_162154_2711_v150.jpg"},{"title":"[e스포츠人] KT 롤스터 곽준혁 \"경기에 대한 소중함 깨달아...우승 노린다\" (테크M ─ 피플)","contents":"이소라 기자","link":"https://www.techm.kr/news/articleView.html?idxno=125476","retrieved":1717337636975,"image":"https://www.techm.kr/news/thumbnail/202406/125476_161840_5533_v150.jpg"},{"title":"[템터뷰] '인생네컷'의 최종목표는? IT 활용한 '포토 라이프 플랫폼' (테크M ─ 피플)","contents":"배수현 기자","link":"https://www.techm.kr/news/articleView.html?idxno=125453","retrieved":1717230420000,"image":"https://www.techm.kr/news/thumbnail/202405/125453_161790_219_v150.jpg"},{"title":"호암재단 '삼성호암상 시상식' 개최…여성 수상자 4명, 역대 '최대' (테크M ─ 피플)","contents":"배수현 기자","link":"https://www.techm.kr/news/articleView.html?idxno=125457","retrieved":1717147115647,"image":"https://www.techm.kr/news/thumbnail/202405/125457_161796_5941_v150.jpg"},{"title":"[부고] 조현기 씨(뉴스1 정치부 기자) 조모상 (테크M ─ 피플)","contents":"이수호 기자","retrieved":1718241302695},{"title":"[부고] 조태진(비즈니스포스트 편집국장)씨 자녀상 (테크M ─ 피플)","contents":"허준 편집장","retrieved":1717065840000},{"title":"[부고] 김택진(엔씨소프트 대표)씨 부친상 (테크M ─ 피플)","contents":"임경호 기자","retrieved":1718241302709},{"title":"[e스포츠人] 아쉬운 성적 기록한 광동 선수단 \"배운 것 많아...시즌4는 다를 것\" (테크M ─ 피플)","contents":"이소라 기자","link":"https://www.techm.kr/news/articleView.html?idxno=125156","retrieved":1716740421296,"image":"https://www.techm.kr/news/thumbnail/202405/125156_161301_5456_v150.jpg"},{"title":"이재용 삼성 회장, 리창 中총리와 별도 면담…\"코로나 위기극복 도움 감사\"(종합) (테크M ─ 피플)","contents":"남도영 기자","link":"https://www.techm.kr/news/articleView.html?idxno=125154","retrieved":1716732833251,"image":"https://www.techm.kr/news/thumbnail/202405/125154_161295_1915_v150.jpg"},{"title":"파나소닉코리아, 콤팩트 풀프레임 미러리스 '루믹스 S9' 출시 (테크M ─ 라이프)","contents":"남도영 기자","link":"https://www.techm.kr/news/articleView.html?idxno=125945","retrieved":1718183910174,"image":"https://www.techm.kr/news/thumbnail/202406/125945_162604_1815_v150.jpg"},{"title":"무신사, 상시 고할인 판매 상품 점검 '전수조사'...소비자 피해 막는다 (테크M ─ 라이프)","contents":"이수호 기자","link":"https://www.techm.kr/news/articleView.html?idxno=125935","retrieved":1718169390153,"image":"https://www.techm.kr/news/thumbnail/202406/125935_162587_445_v150.jpg"},{"title":"대표주자 농심 vs 수출역군 삼양....라면한류 주도권 두고 경쟁 '치열' (테크M ─ 라이프)","contents":"이수호 기자","link":"https://www.techm.kr/news/articleView.html?idxno=125933","retrieved":1718152920000,"image":"https://www.techm.kr/news/thumbnail/202406/125933_162582_425_v150.jpg"},{"title":"'더현대' 일본에서 흥행몰이...K콘텐츠 열풍 타고 한달 매출 13억원 돌파 (테크M ─ 라이프)","contents":"이소라 기자","link":"https://www.techm.kr/news/articleView.html?idxno=125909","retrieved":1718186760000,"image":"https://www.techm.kr/news/thumbnail/202406/125909_162553_155_v150.jpg"},{"title":"이랜드-에어인천, K패션 글로벌 경쟁력 강화 위해 맞손 (테크M ─ 라이프)","contents":"이소라 기자","link":"https://www.techm.kr/news/articleView.html?idxno=125895","retrieved":1718104539385,"image":"https://www.techm.kr/news/thumbnail/202406/125895_162530_2710_v150.jpg"},{"title":"돌봄공백 아동과 온정 나눈 CJ제일제당...햇반 솥밥 1만개 기 (테크M ─ 라이프)","contents":"이소라 기자","link":"https://www.techm.kr/news/articleView.html?idxno=125880","retrieved":1718087007588,"image":"https://www.techm.kr/news/thumbnail/202406/125880_162499_3528_v150.jpg"},{"title":"야놀자 플랫폼, 코레일 MaaS 구축 위해 협력체계 강화 (테크M ─ 라이프)","contents":"이수호 기자","link":"https://www.techm.kr/news/articleView.html?idxno=125878","retrieved":1718083099995,"image":"https://www.techm.kr/news/thumbnail/202406/125878_162487_1118_v150.jpg"},{"title":"[같이사소] 여름 준비 아직 안하셨어요?...쿠팡-티몬-위메프에서 준비한 여름 기획전 (테크M ─ 라이프)","contents":"이소라 기자","link":"https://www.techm.kr/news/articleView.html?idxno=125847","retrieved":1718102640000,"image":"https://www.techm.kr/news/thumbnail/202406/125847_162460_4119_v150.jpg"},{"title":"지그재그, 이너웨어 연중 최대 규모 할인 진행 (테크M ─ 라이프)","contents":"이수호 기자","link":"https://www.techm.kr/news/articleView.html?idxno=125855","retrieved":1718101560000,"image":"https://www.techm.kr/news/thumbnail/202406/125855_162459_2656_v150.jpg"},{"title":"와디즈, 크라우드펀딩 성공 돕는 '통합 광고센터' 선보인다 (테크M ─ 라이프)","contents":"허준 편집장","link":"https://www.techm.kr/news/articleView.html?idxno=125809","retrieved":1718019780000,"image":"https://www.techm.kr/news/thumbnail/202406/125809_162357_4311_v150.jpg"},{"title":"'선재 앓이' 빠진 소비자 잡는다...CJ온스타일, '선재 업고 튀어' 굿즈 온라인 최초 론칭 (테크M ─ 라이프)","contents":"이소라 기자","link":"https://www.techm.kr/news/articleView.html?idxno=125788","retrieved":1718014140000,"image":"https://www.techm.kr/news/thumbnail/202406/125788_162335_451_v150.jpg"},{"title":"무신사, '뉴발란스 530 데이' 캠페인 열었다 (테크M ─ 라이프)","contents":"이수호 기자","link":"https://www.techm.kr/news/articleView.html?idxno=125775","retrieved":1718011680000,"image":"https://www.techm.kr/news/thumbnail/202406/125775_162321_2856_v150.jpg"},{"title":"\"정가 2배 부풀리고 상시 고할인\"···고물가에 할인율 '미끼' 상품 주의보 (테크M ─ 라이프)","contents":"이수호 기자","link":"https://www.techm.kr/news/articleView.html?idxno=125736","retrieved":1717822800000,"image":"https://www.techm.kr/news/thumbnail/202406/125736_162234_73_v150.jpg"},{"title":"한샘, 분당점 인테리어관 리뉴얼 오픈 (테크M ─ 라이프)","contents":"이수호 기자","link":"https://www.techm.kr/news/articleView.html?idxno=125718","retrieved":1717756140000,"image":"https://www.techm.kr/news/thumbnail/202406/125718_162195_2922_v150.jpg"},{"title":"[글로벌] 노르웨이 국부펀드도 '머스크 60조원대 보상안' 반대 (테크M ─ 리포트)","contents":"김현기 대표","link":"https://www.techm.kr/news/articleView.html?idxno=125861","retrieved":1718083100000,"image":"https://www.techm.kr/news/thumbnail/202406/125861_162527_195_v150.jpg"},{"title":"[글로벌] 볼보, 전기차 생산기지 벨기에로 이전...\"EU-중국 무역전쟁 대비\" (테크M ─ 리포트)","contents":"김현기 대표","link":"https://www.techm.kr/news/articleView.html?idxno=125862","retrieved":1718083100003,"image":"https://www.techm.kr/news/thumbnail/202406/125862_162526_1839_v150.jpg"},{"title":"[글로벌] 독일서 가장 작은 유인원 화석 발견...\"다른 유인원 종과 공존했을 것\" (테크M ─ 리포트)","contents":"김현기 대표","link":"https://www.techm.kr/news/articleView.html?idxno=125863","retrieved":1718083100004,"image":"https://www.techm.kr/news/thumbnail/202406/125863_162525_1818_v150.jpg"},{"title":"[글로벌] 스페이스X 우주선 '스타십', 지구 궤도 비행 후 귀환 성공...\"화성에 한발 더\" (테크M ─ 리포트)","contents":"김현기 대표","link":"https://www.techm.kr/news/articleView.html?idxno=125749","retrieved":1717842360000,"image":"https://www.techm.kr/news/thumbnail/202406/125749_162264_2619_v150.jpg"},{"title":"[글로벌] 中, 자국 9개 업체에 자율주행 시범 운행 허가...\"자율주행 상용화 속도\" (테크M ─ 리포트)","contents":"김현기 대표","link":"https://www.techm.kr/news/articleView.html?idxno=125748","retrieved":1717842300000,"image":"https://www.techm.kr/news/thumbnail/202406/125748_162263_258_v150.jpg"},{"title":"[글로벌] 美 연방규제당국, 엔비디아·MS·오픈AI 등에 AI 반독점 조사 (테크M ─ 리포트)","contents":"김현기 대표","link":"https://www.techm.kr/news/articleView.html?idxno=125747","retrieved":1717842240000,"image":"https://www.techm.kr/news/thumbnail/202406/125747_162262_2357_v150.jpg"},{"title":"[글로벌] 일론 머스크 \"테슬라, 올해 엔비디아 칩 구매에 최대 5조원 지출\" (테크M ─ 리포트)","contents":"김현기 대표","link":"https://www.techm.kr/news/articleView.html?idxno=125692","retrieved":1717662068309,"image":"https://www.techm.kr/news/thumbnail/202406/125692_162164_2941_v150.jpg"},{"title":"[글로벌] 美 MS, 올해 벌써 1900명 해고...\"이어지는 빅테크 감원\" (테크M ─ 리포트)","contents":"김현기 대표","link":"https://www.techm.kr/news/articleView.html?idxno=125691","retrieved":1717662068316,"image":"https://www.techm.kr/news/thumbnail/202406/125691_162163_2850_v150.jpg"},{"title":"[글로벌] \"AI가 인류 멸종 초래할 수 있어\"...오픈AI·구글 딥마인드 전·현직 직원의 '경고' (테크M ─ 리포트)","contents":"김현기 대표","link":"https://www.techm.kr/news/articleView.html?idxno=125690","retrieved":1717662068316,"image":"https://www.techm.kr/news/thumbnail/202406/125690_162162_2712_v150.jpg"},{"title":"[글로벌] 제임스웹 망원경,가장 오래된 은하 포착...\"약 137억년 전부터 존재\" (테크M ─ 리포트)","contents":"김현기 대표","link":"https://www.techm.kr/news/articleView.html?idxno=125597","retrieved":1717489281333,"image":"https://www.techm.kr/news/thumbnail/202406/125597_162016_217_v150.jpg"},{"title":"[글로벌] 마이크로소프트 검색서비스 '빙', 다운로드 15배 증가...\"압도적 1위\" (테크M ─ 리포트)","contents":"김현기 대표","link":"https://www.techm.kr/news/articleView.html?idxno=125596","retrieved":1717489281333,"image":"https://www.techm.kr/news/thumbnail/202406/125596_162014_1951_v150.jpg"},{"title":"[글로벌] EU, 中 테무도 '초대형 플랫폼' 지정...\"알리·테무·쉬인 규제 강화\" (테크M ─ 리포트)","contents":"김현기 대표","link":"https://www.techm.kr/news/articleView.html?idxno=125595","retrieved":1717489281335,"image":"https://www.techm.kr/news/thumbnail/202406/125595_162013_1857_v150.jpg"},{"title":"[글로벌] 오픈AI 前 이사 \"챗GPT 출시도 몰랐다\"...샘 올트먼 축출 이유 설명 (테크M ─ 리포트)","contents":"김현기 대표","link":"https://www.techm.kr/news/articleView.html?idxno=125463","retrieved":1717229880000,"image":"https://www.techm.kr/news/thumbnail/202406/125463_161818_1810_v150.jpg"},{"title":"[글로벌] EU, 中 전기차 관세 발표 7월로 연기...中 '맞불' 검토 (테크M ─ 리포트)","contents":"김현기 대표","link":"https://www.techm.kr/news/articleView.html?idxno=125462","retrieved":1717229820000,"image":"https://www.techm.kr/news/thumbnail/202406/125462_161817_1713_v150.jpg"},{"title":"[게임코인TV] 금융위가 NFT 가이드라인을 발표했다...NFT도 가상자산일까?(2편) (테크M ─ 보는 뉴스)","contents":"이소라 기자","link":"https://www.techm.kr/news/articleView.html?idxno=125953","retrieved":1718201829914,"image":"https://www.techm.kr/news/thumbnail/202406/125953_162630_959_v150.jpg"},{"title":"[게임코인TV] 금융위가 NFT 가이드라인을 발표했다...NFT도 가상자산일까?(1편) (테크M ─ 보는 뉴스)","contents":"이소라 기자","link":"https://www.techm.kr/news/articleView.html?idxno=125896","retrieved":1718119123969,"image":"https://www.techm.kr/news/thumbnail/202406/125896_162531_392_v150.jpg"},{"title":"[카드뉴스] 스마일게이트, MMORPG 로드나인 공개 '무과금으로 성장의 재미를 느낀다' (테크M ─ 보는 뉴스)","contents":"이아령 에디터","link":"https://www.techm.kr/news/articleView.html?idxno=125889","retrieved":1718090192362,"image":"https://www.techm.kr/news/thumbnail/202406/125889_162506_3532_v150.jpg"},{"title":"[카드뉴스] LG CNS, 새로운 도전을 시작하다...해외기업과 손잡고 글로벌 무대로 (테크M ─ 보는 뉴스)","contents":"이아령 에디터","link":"https://www.techm.kr/news/articleView.html?idxno=125833","retrieved":1718003776447,"image":"https://www.techm.kr/news/thumbnail/202406/125833_162412_90_v150.jpg"},{"title":"[게임코인TV] 22대 국회 개원...가상자산 법 다룰 정무위는 누가? (테크M ─ 보는 뉴스)","contents":"이소라 기자","link":"https://www.techm.kr/news/articleView.html?idxno=125768","retrieved":1717936227709,"image":"https://www.techm.kr/news/thumbnail/202406/125768_162309_2154_v150.jpg"},{"title":"[게임코인TV] 새로운 소식 가지고 왔어요!...넷마블 '마브렉스'의 변화(2편) (테크M ─ 보는 뉴스)","contents":"이소라 기자","link":"https://www.techm.kr/news/articleView.html?idxno=125760","retrieved":1717896540000,"image":"https://www.techm.kr/news/thumbnail/202406/125760_162291_2819_v150.jpg"},{"title":"[카드뉴스] 'LG유플러스 볼트업' 공식 출범하고, 전기차 시대 준비한다 (테크M ─ 보는 뉴스)","contents":"이아령 에디터","link":"https://www.techm.kr/news/articleView.html?idxno=125732","retrieved":1717840440000,"image":"https://www.techm.kr/news/thumbnail/202406/125732_162223_2229_v150.jpg"},{"title":"[카드뉴스] 두나무, 블록체인을 활용한 '공정성+ 투명성' 갖춘 추첨 툴 개발 (테크M ─ 보는 뉴스)","contents":"이아령 에디터","link":"https://www.techm.kr/news/articleView.html?idxno=125668","retrieved":1717586079675,"image":"https://www.techm.kr/news/thumbnail/202406/125668_162113_451_v150.jpg"},{"title":"[카드뉴스] 국내 게임업계, 방치형 게임 '키우기' 개발에 집중하는 이유는? (테크M ─ 보는 뉴스)","contents":"이아령 에디터","link":"https://www.techm.kr/news/articleView.html?idxno=125587","retrieved":1717493170016,"image":"https://www.techm.kr/news/thumbnail/202406/125587_161994_3450_v150.jpg"},{"title":"[게임코인TV] 새로운 소식 가지고 왔어요!...넷마블 '마브렉스'의 변화(1편) (테크M ─ 보는 뉴스)","contents":"이소라 기자","link":"https://www.techm.kr/news/articleView.html?idxno=125600","retrieved":1717493170018,"image":"https://www.techm.kr/news/thumbnail/202406/125600_162034_4723_v150.jpg"},{"title":"[카드뉴스] LG전자, 2024 미래교육박람회에서 'AI 기반 에듀테크 솔루션' 선보인다 (테크M ─ 보는 뉴스)","contents":"이아령 에디터","link":"https://www.techm.kr/news/articleView.html?idxno=125455","retrieved":1717139744543,"image":"https://www.techm.kr/news/thumbnail/202405/125455_161779_504_v150.jpg"},{"title":"[카드뉴스] 넷마블, '전작의 명성을 이어갈 수 있을까' MMORPG 레이븐2 정식 출시 (테크M ─ 보는 뉴스)","contents":"이아령 에디터","link":"https://www.techm.kr/news/articleView.html?idxno=125392","retrieved":1717067973179,"image":"https://www.techm.kr/news/thumbnail/202405/125392_161672_644_v150.jpg"},{"title":"[카드뉴스] KT, 안양시와 함께 자율주행버스 '주야로' 시범운행에 나섰다 (테크M ─ 보는 뉴스)","contents":"이아령 에디터","link":"https://www.techm.kr/news/articleView.html?idxno=125340","retrieved":1717063560000,"image":"https://www.techm.kr/news/thumbnail/202405/125340_161582_566_v150.jpg"},{"title":"[게임코인TV] 이더리움 현물 ETF도 SEC 뚫었다...가상자산 제도권 편입 본격화?(2편) (테크M ─ 보는 뉴스)","contents":"이소라 기자","link":"https://www.techm.kr/news/articleView.html?idxno=125317","retrieved":1716982380000,"image":"https://www.techm.kr/news/thumbnail/202405/125317_161557_3212_v150.jpg"}]}