{"title":"테크M ─ 인프라","url":"https://www.techm.kr/news/articleList.html?sc_serial_code=SRN2&view_type=sm","favicon":"https://www.techm.kr/news/favicon.ico","elements":[{"title":"삼성전자, 업계 최고 속도 LPDDR5X 개발 성공…\"온디바이스 AI 최적화\"","contents":"남도영 기자","link":"https://www.techm.kr/news/articleView.html?idxno=123227","retrieved":1713353640000,"image":"https://www.techm.kr/news/thumbnail/202404/123227_158215_3243_v150.jpg"},{"title":"AI 거버넌스 강조한 SKT...\"글로벌 AI 컴퍼니 주춧돌\"","contents":"이성우 기자","link":"https://www.techm.kr/news/articleView.html?idxno=123221","retrieved":1713353220000,"image":"https://www.techm.kr/news/thumbnail/202404/123221_158209_1015_v150.jpg"},{"title":"소프트캠프, 에쓰핀테크놀로지와 생성형 AI 보안 '맞손'","contents":"남도영 기자","link":"https://www.techm.kr/news/articleView.html?idxno=123224","retrieved":1713353040000,"image":"https://www.techm.kr/news/thumbnail/202404/123224_158212_2246_v150.jpg"},{"title":"국내 보안기업 '공동 기업 설명회' 연다...\"보안산업 가치 재조명\"","contents":"남도영 기자","link":"https://www.techm.kr/news/articleView.html?idxno=123222","retrieved":1713352620000,"image":"https://www.techm.kr/news/thumbnail/202404/123222_158210_1427_v150.jpg"},{"title":"CJ올리브네트웍스, 마케팅 콘퍼런스 'GRB 서울' 성료","contents":"남도영 기자","link":"https://www.techm.kr/news/articleView.html?idxno=123220","retrieved":1713352080000,"image":"https://www.techm.kr/news/thumbnail/202404/123220_158208_79_v150.jpg"},{"title":"삼성SDS, 공공분야 '하이퍼오토메이션' 혁신 나선다","contents":"남도영 기자","link":"https://www.techm.kr/news/articleView.html?idxno=123219","retrieved":1713351720000,"image":"https://www.techm.kr/news/thumbnail/202404/123219_158207_129_v150.jpg"},{"title":"x86 vs. ARM, 뜨거워지는 'AI PC' 주도권 경쟁","contents":"남도영 기자","link":"https://www.techm.kr/news/articleView.html?idxno=123215","retrieved":1713349860000,"image":"https://www.techm.kr/news/thumbnail/202404/123215_158201_2556_v150.jpg"},{"title":"KT, 스마트폰 업무 앱 제어 플랫폼 개발...\"보안 강화\"","contents":"이성우 기자","link":"https://www.techm.kr/news/articleView.html?idxno=123211","retrieved":1713348180000,"image":"https://www.techm.kr/news/thumbnail/202404/123211_158196_5526_v150.jpg"},{"title":"KT 이니텍, 보안성 강화한 기업용 생성형 AI '시큐어 AI' 출시","contents":"이성우 기자","link":"https://www.techm.kr/news/articleView.html?idxno=123213","retrieved":1713348180000,"image":"https://www.techm.kr/news/thumbnail/202404/123213_158199_047_v150.jpg"},{"title":"삼성전자, '유로쿠치나 2024' 참여···유럽 특화 빌트인 제품 선보여","contents":"배수현 기자","link":"https://www.techm.kr/news/articleView.html?idxno=123209","retrieved":1713347700000,"image":"https://www.techm.kr/news/thumbnail/202404/123209_158192_4820_v150.jpg"},{"title":"삼성스토어, '제 1회 삼성스토어 이사박람회' 개최···삼성 AI 가전 체험 가능","contents":"배수현 기자","link":"https://www.techm.kr/news/articleView.html?idxno=123206","retrieved":1713347700000,"image":"https://www.techm.kr/news/thumbnail/202404/123206_158190_3040_v150.jpg"},{"title":"'U+무너쉴드'가 보이스피싱·스미싱 피해 막는다","contents":"이성우 기자","link":"https://www.techm.kr/news/articleView.html?idxno=123203","retrieved":1713347700000,"image":"https://www.techm.kr/news/thumbnail/202404/123203_158195_525_v150.jpg"},{"title":"유니티 '슈퍼소닉 슈퍼스프링' 게임 개발자 대상 콘테스트 열었다","contents":"이수호 기자","link":"https://www.techm.kr/news/articleView.html?idxno=123208","retrieved":1713346620000,"image":"https://www.techm.kr/news/thumbnail/202404/123208_158191_3626_v150.jpg"},{"title":"KB국민은행, 우리 아이 'KB스타뱅킹 시작하기' 이벤트 열었다","contents":"이수호 기자","link":"https://www.techm.kr/news/articleView.html?idxno=123207","retrieved":1713346140000,"image":"https://www.techm.kr/news/thumbnail/202404/123207_158189_2928_v150.jpg"}]}