{"title":"테크M ─ 인프라","url":"https://www.techm.kr/news/articleList.html?sc_serial_code=SRN2&view_type=sm","favicon":"https://www.techm.kr/news/favicon.ico","elements":[{"title":"DMZ 자연풍경, 60여개 전시...구글 '스트리트 뷰'에 담는다","contents":"이영아 기자","link":"https://www.techm.kr/news/articleView.html?idxno=107171","retrieved":1677057607955,"image":"https://www.techm.kr/news/thumbnail/202302/107171_129696_2313_v150.jpg"},{"title":"챗GPT 활용 시작한 과기정통부…\"보도자료 제목 챗GPT로 작성\"","contents":"김가은 기자","link":"https://www.techm.kr/news/articleView.html?idxno=107169","retrieved":1677054208320,"image":"https://www.techm.kr/news/thumbnail/202302/107169_129695_931_v150.jpg"},{"title":"\"인건비 통제\" 천명한 네이버 경영진...'채용동결' 현실화","contents":"이영아 기자","link":"https://www.techm.kr/news/articleView.html?idxno=107168","retrieved":1677054208324,"image":"https://www.techm.kr/news/thumbnail/202302/107168_129698_4155_v150.jpg"},{"title":"롯데정보통신 'K-UAM' 실증사업 참여...교통관리·관제 시스템 검증","contents":"남도영 기자","link":"https://www.techm.kr/news/articleView.html?idxno=107165","retrieved":1677054208325,"image":"https://www.techm.kr/news/thumbnail/202302/107165_129676_2945_v150.jpg"},{"title":"'업무·콘텐츠·학업'도 '뚝딱'...일상으로 파고든 '챗GPT'에 활용법 공유 열풍","contents":"김가은 기자","link":"https://www.techm.kr/news/articleView.html?idxno=107159","retrieved":1677054208326,"image":"https://www.techm.kr/news/thumbnail/202302/107159_129699_4211_v150.jpg"},{"title":"[가봤다] 극장에서 확인한 '갤럭시 S23 울트라' 카메라의 압도적 디테일","contents":"남도영 기자","link":"https://www.techm.kr/news/articleView.html?idxno=107157","retrieved":1677050238435,"image":"https://www.techm.kr/news/thumbnail/202302/107157_129702_4247_v150.jpg"},{"title":"정부 압박에 4만원대 '무제한 5G' 내놓은 LG U+…KT도 신규 요금제 출시 검토","contents":"김가은 기자","link":"https://www.techm.kr/news/articleView.html?idxno=107153","retrieved":1677043046349,"image":"https://www.techm.kr/news/thumbnail/202302/107153_129658_5253_v150.jpg"},{"title":"효성인포메이션시스템 'DX센터 시즌3' 오픈...\"AI·데이터 기반 DX 로드맵 제시\"","contents":"남도영 기자","link":"https://www.techm.kr/news/articleView.html?idxno=107147","retrieved":1677065700000,"image":"https://www.techm.kr/news/thumbnail/202302/107147_129644_353_v150.jpg"},{"title":"카카오메이커스, '새가버치' 참여 크루 모집...\"업사이클링 기부\"","contents":"이영아 기자","link":"https://www.techm.kr/news/articleView.html?idxno=107142","retrieved":1677064020000,"image":"https://www.techm.kr/news/thumbnail/202302/107142_129639_456_v150.jpg"},{"title":"\"'통신 환승' 경험 제공\" 토스모바일, 요금제 가입 전국 단위로 확대","contents":"김가은 기자","link":"https://www.techm.kr/news/articleView.html?idxno=107141","retrieved":1677063540000,"image":"https://www.techm.kr/news/thumbnail/202302/107141_129637_5756_v150.jpg"},{"title":"\"기술로 불법 유통 차단\"…네이버웹툰, 아태지역에 '저작권 보호' 알려","contents":"이영아 기자","link":"https://www.techm.kr/news/articleView.html?idxno=107140","retrieved":1677063240000,"image":"https://www.techm.kr/news/thumbnail/202302/107140_129635_5119_v150.jpg"},{"title":"통신3사, 국토부 UAM 실증사업에 모두 참여...'하늘길 경쟁' 본격 점화","contents":"김가은 기자","link":"https://www.techm.kr/news/articleView.html?idxno=107139","retrieved":1677063240000,"image":"https://www.techm.kr/news/thumbnail/202302/107139_129636_5123_v150.jpg"},{"title":"SKT, NTT도코모와 5G·6G 기술 백서 발간…\"6G 시장 공동 개척\"","contents":"김가은 기자","link":"https://www.techm.kr/news/articleView.html?idxno=107137","retrieved":1677060720000,"image":"https://www.techm.kr/news/thumbnail/202302/107137_129631_86_v150.jpg"},{"title":"\"놀면서 공부도 한다\" LG유플러스, 알파세대 특화 메타버스 '키즈토피아' 출시","contents":"김가은 기자","link":"https://www.techm.kr/news/articleView.html?idxno=107135","retrieved":1677060660000,"image":"https://www.techm.kr/news/thumbnail/202302/107135_129629_010_v150.jpg"}]}