{"title":"테크M ─ 전체기사","url":"https://www.techm.kr/news/articleList.html","favicon":"https://www.techm.kr/news/favicon.ico","elements":[{"title":"레노버, AMD 손잡고 '씽크스테이션 P8' 출시…AI 워크스테이션 시장 정조준","contents":"남도영 기자","link":"https://www.techm.kr/news/articleView.html?idxno=122148","retrieved":1711430063398,"image":"https://www.techm.kr/news/thumbnail/202403/122148_156400_1433_v150.jpg"},{"title":"서비스나우, 금융 업계 AI기반 IT 운영 서비스 혁신 지원 본격화한다","contents":"배수현 기자","link":"https://www.techm.kr/news/articleView.html?idxno=122146","retrieved":1711412040000,"image":"https://www.techm.kr/news/thumbnail/202403/122146_156397_354_v150.jpg"},{"title":"과기정통부, 중소 중견 알뜰폰 사업자 전파사용료 감면 1년 연장","contents":"배수현 기자","link":"https://www.techm.kr/news/articleView.html?idxno=122135","retrieved":1711411980000,"image":"https://www.techm.kr/news/thumbnail/202403/122135_156398_1350_v150.jpg"},{"title":"슬링, 학습 앱 '오르조' 앱스토어 교육 부문 인기·매출 순위 1위 달성","contents":"배수현 기자","link":"https://www.techm.kr/news/articleView.html?idxno=122141","retrieved":1711411440000,"image":"https://www.techm.kr/news/thumbnail/202403/122141_156394_545_v150.jpg"},{"title":"레노버, AMD 최신 칩셋 탑재한 '씽크스테이션 P8' 워크스테이션 출시","contents":"남도영 기자","link":"https://www.techm.kr/news/articleView.html?idxno=122145","retrieved":1711454220000,"image":"https://www.techm.kr/news/thumbnail/202403/122145_156395_5528_v150.jpg"},{"title":"[네이버 주총] 네이버웹툰 나스닥 도전 \"새로운 가치 창출 가능...분할상장 아니다\"","contents":"이성우 기자","link":"https://www.techm.kr/news/articleView.html?idxno=122142","retrieved":1711454100000,"image":"https://www.techm.kr/news/thumbnail/202403/122142_156392_5145_v150.jpg"},{"title":"[SK텔레콤 주총] AI 거버넌스 원칙 'T.H.E AI' 공개…\"고객 보호·신뢰 강화 우선\"","contents":"조성준 기자","link":"https://www.techm.kr/news/articleView.html?idxno=122143","retrieved":1711453920000,"image":"https://www.techm.kr/news/thumbnail/202403/122143_156393_5158_v150.jpg"},{"title":"[네이버 주총] 알리-테무 침공 걱정 없다...최수연 대표 \"네이버엔 위기이자 기회\"","contents":"이성우 기자","link":"https://www.techm.kr/news/articleView.html?idxno=122138","retrieved":1711453620000,"image":"https://www.techm.kr/news/thumbnail/202403/122138_156386_3935_v150.jpg"},{"title":"[글로벌] \"中 전기차 BYD, 글로벌 시장에서 여러 한계 직면할 듯\"","contents":"김현기 대표","link":"https://www.techm.kr/news/articleView.html?idxno=122140","retrieved":1711453560000,"image":"https://www.techm.kr/news/thumbnail/202403/122140_156390_4535_v150.jpg"},{"title":"[글로벌] 머스크가 인수한 엑스, 일일 이용자 수 감소세 지속","contents":"김현기 대표","link":"https://www.techm.kr/news/articleView.html?idxno=122139","retrieved":1711453500000,"image":"https://www.techm.kr/news/thumbnail/202403/122139_156389_4432_v150.jpg"},{"title":"[글로벌] \"애플, 中 바이두와 AI 탑재 논의\"...판매 부진 끊어내나","contents":"김현기 대표","link":"https://www.techm.kr/news/articleView.html?idxno=122137","retrieved":1711453440000,"image":"https://www.techm.kr/news/thumbnail/202403/122137_156388_4019_v150.jpg"},{"title":"'가성비 뷰티' 열풍 이끄는 지그재그...1포 300원, 이즈앤트리 어니언 부스터 샷 단독 출시","contents":"김소은 기자","link":"https://www.techm.kr/news/articleView.html?idxno=122136","retrieved":1711453080000,"image":"https://www.techm.kr/news/thumbnail/202403/122136_156385_3131_v150.jpg"},{"title":"\"포토부스에 AI 콘텐츠 결합\"...비브스튜디오스, 대승인터컴과 전략적 협업","contents":"김소은 기자","link":"https://www.techm.kr/news/articleView.html?idxno=122132","retrieved":1711452480000,"image":"https://www.techm.kr/news/thumbnail/202403/122132_156384_2117_v150.jpg"},{"title":"[네이버 주총] 최수연 대표 \"AI 시대, 네이버는 '생성형 검색 서비스'로 간다\"","contents":"이성우 기자","link":"https://www.techm.kr/news/articleView.html?idxno=122133","retrieved":1711452300000,"image":"https://www.techm.kr/news/thumbnail/202403/122133_156382_162_v150.jpg"},{"title":"스파크랩, '배치 프로그램' 23기 모집...신생 스타트업 육성한다","contents":"배수현 기자","link":"https://www.techm.kr/news/articleView.html?idxno=122131","retrieved":1711452180000,"image":"https://www.techm.kr/news/thumbnail/202403/122131_156383_1913_v150.jpg"},{"title":"네이버웹툰 '매일+'에서 레전드 웹툰 '열혈강호 리마스터' 본다","contents":"김소은 기자","link":"https://www.techm.kr/news/articleView.html?idxno=122130","retrieved":1711452180000,"image":"https://www.techm.kr/news/thumbnail/202403/122130_156381_1227_v150.jpg"},{"title":"KT, 마이프랜차이즈와 '맞손'...창업 정보 제공하는 '프랜차이즈TV' 출시","contents":"배수현 기자","link":"https://www.techm.kr/news/articleView.html?idxno=122127","retrieved":1711452060000,"image":"https://www.techm.kr/news/thumbnail/202403/122127_156379_955_v150.jpg"},{"title":"KT, 과기정통부 '중소기업 클라우드 서비스 보급·확산 사업' 참여","contents":"배수현 기자","link":"https://www.techm.kr/news/articleView.html?idxno=122125","retrieved":1711452000000,"image":"https://www.techm.kr/news/thumbnail/202403/122125_156378_58_v150.jpg"},{"title":"[SK텔레콤 주총] 유영상 대표 \"전환지원금 경쟁해도 주주가치 훼손 없을 것\"","contents":"조성준 기자","link":"https://www.techm.kr/news/articleView.html?idxno=122129","retrieved":1711451580000,"image":"https://www.techm.kr/news/thumbnail/202403/122129_156380_1128_v150.jpg"},{"title":"LG유플러스 마음관리 플랫폼 '답다'...출시 6개월 만 가입자 2만명 돌파","contents":"배수현 기자","link":"https://www.techm.kr/news/articleView.html?idxno=122122","retrieved":1711450920000,"image":"https://www.techm.kr/news/thumbnail/202403/122122_156374_5249_v150.jpg"}]}