{"title":"테크M ─ 라이프","url":"https://www.techm.kr/news/articleList.html?sc_serial_code=SRN6&view_type=sm","favicon":"https://www.techm.kr/news/favicon.ico","elements":[{"title":"CJ제일제당, 케이스타쥬 2기 모집...'한식' 세계에 알린다","contents":"이수호 기자","link":"https://www.techm.kr/news/articleView.html?idxno=121462","retrieved":1710138098400,"image":"https://www.techm.kr/news/thumbnail/202403/121462_155174_3339_v150.jpg"},{"title":"카카오 지그재그, 뷰티위크 개최... 스킨케어 거래액 '껑충'","contents":"이수호 기자","link":"https://www.techm.kr/news/articleView.html?idxno=121461","retrieved":1710138098401,"image":"https://www.techm.kr/news/thumbnail/202403/121461_155172_3121_v150.jpg"},{"title":"현대백화점그룹 기업대학, 디지털 인재 키운다","contents":"이수호 기자","link":"https://www.techm.kr/news/articleView.html?idxno=121460","retrieved":1710138098403,"image":"https://www.techm.kr/news/thumbnail/202403/121460_155169_3020_v150.jpg"},{"title":"농심, 누들핏 사발면맛 2종 출시","contents":"이수호 기자","link":"https://www.techm.kr/news/articleView.html?idxno=121459","retrieved":1710138098404,"image":"https://www.techm.kr/news/thumbnail/202403/121459_155168_2840_v150.jpg"},{"title":"LG전자, 2024년형 'LG 사운드바' 출시","contents":"남도영 기자","link":"https://www.techm.kr/news/articleView.html?idxno=121449","retrieved":1710134217050,"image":"https://www.techm.kr/news/thumbnail/202403/121449_155151_4638_v150.jpg"},{"title":"[삼성 세탁건조기 톺아보기] 한국 넘어 글로벌 시장 개척...\"AI, 실생활에 밀착\"(종합)","contents":"이소라 기자","link":"https://www.techm.kr/news/articleView.html?idxno=121439","retrieved":1710118740000,"image":"https://www.techm.kr/news/thumbnail/202403/121439_155203_1513_v150.jpg"},{"title":"\"쿠팡 대신 알리 키운다\" 中 손 잡은 CJ제일제당...토종 유통가 근심 커졌다","contents":"이수호 기자","link":"https://www.techm.kr/news/articleView.html?idxno=121442","retrieved":1710118740000,"image":"https://www.techm.kr/news/thumbnail/202403/121442_155145_5837_v150.jpg"},{"title":"[가봤다] '반려견 천국' 강아지와 함께한 수원 스타필드...오전부터 '오픈런'","contents":"이수호 기자","link":"https://www.techm.kr/news/articleView.html?idxno=121438","retrieved":1710117180000,"image":"https://www.techm.kr/news/thumbnail/202403/121438_155204_1537_v150.jpg"},{"title":"[삼성 세탁건조기 톺아보기] 세탁세제도 최적화했다...퍼실과 콜라보에 '눈길'","contents":"이소라 기자","link":"https://www.techm.kr/news/articleView.html?idxno=121437","retrieved":1710117060000,"image":"https://www.techm.kr/news/thumbnail/202403/121437_155134_1212_v150.jpg"},{"title":"[삼성 세탁건조기 톺아보기] 다재다능 AI 기능 구현...갤럭시S24와 '닮았다'","contents":"이소라 기자","link":"https://www.techm.kr/news/articleView.html?idxno=121436","retrieved":1710117060000,"image":"https://www.techm.kr/news/thumbnail/202403/121436_155133_949_v150.jpg"},{"title":"[삼성 세탁건조기 톺아보기] 에너지 절약-탄소배출에 대한 고민 엿보이는 기술 적용","contents":"이소라 기자","link":"https://www.techm.kr/news/articleView.html?idxno=121435","retrieved":1710117060000,"image":"https://www.techm.kr/news/thumbnail/202403/121435_155132_841_v150.jpg"},{"title":"[삼성 세탁건조기 톺아보기] 3년의 기다림, 국내 최대 용량 비스포크 AI 콤보 탄생","contents":"이소라 기자","link":"https://www.techm.kr/news/articleView.html?idxno=121434","retrieved":1710117060000,"image":"https://www.techm.kr/news/thumbnail/202403/121434_155131_34_v150.jpg"},{"title":"LG전자, '고효율 히트펌프' 기술 앞세워 유럽 냉난방 공조 시장 공략 가속","contents":"남도영 기자","link":"https://www.techm.kr/news/articleView.html?idxno=121432","retrieved":1710155400000,"image":"https://www.techm.kr/news/thumbnail/202403/121432_155128_1014_v150.jpg"},{"title":"키즈노트, 공공기관 정책 지원 등으로 유치원 교육 환경 개선 기능 고도화","contents":"김소은 기자","link":"https://www.techm.kr/news/articleView.html?idxno=121425","retrieved":1710155280000,"image":"https://www.techm.kr/news/thumbnail/202403/121425_155122_4911_v150.jpg"}]}