{"title":"테크M ─ 리포트","url":"https://www.techm.kr/news/articleList.html?sc_serial_code=SRN7&view_type=sm","favicon":"https://www.techm.kr/news/favicon.ico","elements":[{"title":"[글로벌] \"AI 가짜뉴스 우려\"...구글, 정치 광고에 AI 사용 표시 의무화","contents":"김현기 대표","link":"https://www.techm.kr/news/articleView.html?idxno=114272","retrieved":1694256480000,"image":"https://www.techm.kr/news/thumbnail/202309/114272_142558_470_v150.jpg"},{"title":"[글로벌] 일본, 달 탐사선 발사 성공...5번째 '달 착륙국' 될까","contents":"김현기 대표","link":"https://www.techm.kr/news/articleView.html?idxno=114271","retrieved":1694256360000,"image":"https://www.techm.kr/news/thumbnail/202309/114271_142552_4528_v150.jpg"},{"title":"[글로벌] 아이폰15 출격 앞둔 애플, 중국발 리스크에 '휘청'","contents":"김현기 대표","link":"https://www.techm.kr/news/articleView.html?idxno=114270","retrieved":1694256240000,"image":"https://www.techm.kr/news/thumbnail/202309/114270_142551_4327_v150.jpg"},{"title":"[글로벌] 중국, '반도체 자립' 속도 내나...\"55조원 규모 기금 조성\"","contents":"김현기 대표","link":"https://www.techm.kr/news/articleView.html?idxno=114228","retrieved":1694168880000,"image":"https://www.techm.kr/news/thumbnail/202309/114228_142481_2759_v150.jpg"},{"title":"[글로벌] \"아마존, 美 경쟁 당국과 네번째 소송전 눈앞\"","contents":"김현기 대표","link":"https://www.techm.kr/news/articleView.html?idxno=114227","retrieved":1694168820000,"image":"https://www.techm.kr/news/thumbnail/202309/114227_142480_2658_v150.jpg"},{"title":"[글로벌] 유튜브, '20억명 이용자' 쇼츠 인기에 수익 악화 우려","contents":"김현기 대표","link":"https://www.techm.kr/news/articleView.html?idxno=114226","retrieved":1694168760000,"image":"https://www.techm.kr/news/thumbnail/202309/114226_142479_2537_v150.jpg"},{"title":"[글로벌] 美 상무부 \"中에 쓸 채찍 있어...AI 반도체 수출은 안돼\"","contents":"김현기 대표","link":"https://www.techm.kr/news/articleView.html?idxno=114151","retrieved":1693902345842,"image":"https://www.techm.kr/news/thumbnail/202309/114151_142363_5739_v150.jpg"},{"title":"[글로벌] EU 규제에 시달린 메타, 유료 버전 페이스북-인스타그램 내놓을까","contents":"김현기 대표","link":"https://www.techm.kr/news/articleView.html?idxno=114150","retrieved":1693902345844,"image":"https://www.techm.kr/news/thumbnail/202309/114150_142364_585_v150.jpg"},{"title":"[글로벌] 중국판 챗GPT '어니봇', 대만-위구르 질문에 '횡설수설'","contents":"김현기 대표","link":"https://www.techm.kr/news/articleView.html?idxno=114149","retrieved":1693902345849,"image":"https://www.techm.kr/news/thumbnail/202309/114149_142365_5821_v150.jpg"},{"title":"[글로벌] \"반도체 특허 공유하자\"...中 9개사, 'RISC-V' 동맹 결성","contents":"김현기 대표","link":"https://www.techm.kr/news/articleView.html?idxno=114055","retrieved":1693654080000,"image":"https://www.techm.kr/news/thumbnail/202309/114055_142184_2759_v150.jpg"},{"title":"[글로벌] 중국 이어 중동도...美, 엔비디아 수출 제한 확대한다","contents":"김현기 대표","link":"https://www.techm.kr/news/articleView.html?idxno=114054","retrieved":1693654020000,"image":"https://www.techm.kr/news/thumbnail/202309/114054_142183_2649_v150.jpg"},{"title":"[글로벌] 일론 머스크, 집 짓는데 회삿돈 썼나...美 검찰·금융당국이 조사한다","contents":"김현기 대표","link":"https://www.techm.kr/news/articleView.html?idxno=114053","retrieved":1693653960000,"image":"https://www.techm.kr/news/thumbnail/202309/114053_142182_2526_v150.jpg"},{"title":"[글로벌] 인스타그램 제친 中 틱톡...\"2년 뒤 美 최대 SNS 될 것\"","contents":"김현기 대표","link":"https://www.techm.kr/news/articleView.html?idxno=114000","retrieved":1693473432206,"image":"https://www.techm.kr/news/thumbnail/202308/114000_142083_2418_v150.jpg"},{"title":"[글로벌] 아마존 CEO \"주 3일 사무실 출근 싫으면 퇴사하라\"","contents":"김현기 대표","link":"https://www.techm.kr/news/articleView.html?idxno=113999","retrieved":1693473432219,"image":"https://www.techm.kr/news/thumbnail/202308/113999_142082_2312_v150.jpg"}]}